{
  "animeTitle": "Akuma-kun الحلقة 1",
  "episodes": [
    {
      "number": 1,
      "title": "الحلقة 1",
      "date": "2025-07-17 17:53:55",
      "link": "https://abdo12249.github.io/1/test1/المشاهده.html?id=akuma-kun&episode=1",
      "image": "https://abdo12249.github.io/1/images/akuma-kun.webp",
      "servers": [
        {
          "serverName": "megamax",
          "url": "https://megamax.me/iframe/We00IxsXbUCcO"
        },
        {
          "serverName": "megamax",
          "url": "https://megamax.me/iframe/We00IxsXbUCcO"
        },
        {
          "serverName": "mega بدون اعلانات - FHD",
          "url": "https://mega.nz/embed/SM1THZTZ!aVea7sruQJMpzf95FHR_5lDDCJscNoUBFgET1KM5gjs"
        },
        {
          "serverName": "uqload - FHD",
          "url": "https://uqload.net/embed-vyskrilm1y2c.html"
        },
        {
          "serverName": "Google drive - FHD",
          "url": "https://drive.google.com/file/d/1ZigBLL9gV2jySmItm0fU3lrYrcXJZ4qL/preview"
        },
        {
          "serverName": "Mp4upload - FHD",
          "url": "https://www.mp4upload.com/embed-kmem2zn8pw7a.html"
        }
      ]
    },
    {
      "number": 2,
      "title": "الحلقة 2",
      "date": "2025-07-17 17:53:55",
      "link": "https://abdo12249.github.io/1/test1/المشاهده.html?id=akuma-kun&episode=2",
      "image": "https://abdo12249.github.io/1/images/akuma-kun.webp",
      "servers": [
        {
          "serverName": "megamax",
          "url": "https://megamax.me/iframe/SeRUFRc95C68q"
        },
        {
          "serverName": "megamax",
          "url": "https://megamax.me/iframe/SeRUFRc95C68q"
        },
        {
          "serverName": "mega بدون اعلانات - FHD",
          "url": "https://mega.nz/embed/nM0EBLKY!d4KCUAiar0xUPr7enl16GJi7GkZ1DAZxdM4zGHss4fA"
        },
        {
          "serverName": "uqload - FHD",
          "url": "https://uqload.net/embed-sesgqn0s27un.html"
        },
        {
          "serverName": "Google drive - FHD",
          "url": "https://drive.google.com/file/d/1RA0eREIloErszRqDV06O86KWc3Ttr1jz/preview"
        },
        {
          "serverName": "Mp4upload - FHD",
          "url": "https://www.mp4upload.com/embed-qgev7civkrn7.html"
        }
      ]
    },
    {
      "number": 3,
      "title": "الحلقة 3",
      "date": "2025-07-17 17:53:56",
      "link": "https://abdo12249.github.io/1/test1/المشاهده.html?id=akuma-kun&episode=3",
      "image": "https://abdo12249.github.io/1/images/akuma-kun.webp",
      "servers": [
        {
          "serverName": "megamax",
          "url": "https://megamax.me/iframe/Jtj0oKoKUHu09"
        },
        {
          "serverName": "megamax",
          "url": "https://megamax.me/iframe/Jtj0oKoKUHu09"
        },
        {
          "serverName": "mega بدون اعلانات - FHD",
          "url": "https://mega.nz/embed/3JUAxKCI!trpzB-LVJ7X7XSpXCSHzb58xwGCOJ4hicR98XrE09Xk"
        },
        {
          "serverName": "uqload - FHD",
          "url": "https://uqload.net/embed-bcurzlbvlogg.html"
        },
        {
          "serverName": "Google drive - FHD",
          "url": "https://drive.google.com/file/d/1aE53FiIXpNufJZhkXSbkICfzO3ZH8UCp/preview"
        },
        {
          "serverName": "Mp4upload - FHD",
          "url": "https://www.mp4upload.com/embed-119ymedlsfpn.html"
        }
      ]
    },
    {
      "number": 4,
      "title": "الحلقة 4",
      "date": "2025-07-17 17:53:56",
      "link": "https://abdo12249.github.io/1/test1/المشاهده.html?id=akuma-kun&episode=4",
      "image": "https://abdo12249.github.io/1/images/akuma-kun.webp",
      "servers": [
        {
          "serverName": "megamax",
          "url": "https://megamax.me/iframe/vD3Ldrp41MGJ2"
        },
        {
          "serverName": "megamax",
          "url": "https://megamax.me/iframe/vD3Ldrp41MGJ2"
        },
        {
          "serverName": "mega بدون اعلانات - FHD",
          "url": "https://mega.nz/embed/LdExQQKK!xUTWLBMRoho_y4vPJlkLQ4d4pJ9BQUP6gyNczn54aA0"
        },
        {
          "serverName": "uqload - FHD",
          "url": "https://uqload.net/embed-eutdknzyxj8l.html"
        },
        {
          "serverName": "Google drive - FHD",
          "url": "https://drive.google.com/file/d/1FZnG7NmmWmt7wtZpBDL9_SyWTdeMylSG/preview"
        },
        {
          "serverName": "Mp4upload - FHD",
          "url": "https://www.mp4upload.com/embed-ju3wisrdurzs.html"
        }
      ]
    },
    {
      "number": 5,
      "title": "الحلقة 5",
      "date": "2025-07-17 17:53:55",
      "link": "https://abdo12249.github.io/1/test1/المشاهده.html?id=akuma-kun&episode=5",
      "image": "https://abdo12249.github.io/1/images/akuma-kun.webp",
      "servers": [
        {
          "serverName": "megamax",
          "url": "https://megamax.me/iframe/ZfHPWossYpBup"
        },
        {
          "serverName": "megamax",
          "url": "https://megamax.me/iframe/ZfHPWossYpBup"
        },
        {
          "serverName": "mega بدون اعلانات - FHD",
          "url": "https://mega.nz/embed/SJVF0aLA!c6V2TJIvb1g00zViqhah5jZaQ1dp1g956P0x6A_5jGg"
        },
        {
          "serverName": "uqload - FHD",
          "url": "https://uqload.net/embed-37avf3iho0uy.html"
        },
        {
          "serverName": "Google drive - FHD",
          "url": "https://drive.google.com/file/d/1G_065Ww7D90zWQj8KBOSVUpBlQqlTSWD/preview"
        },
        {
          "serverName": "Mp4upload - FHD",
          "url": "https://www.mp4upload.com/embed-ewxylzhvkwqp.html"
        }
      ]
    },
    {
      "number": 6,
      "title": "الحلقة 6",
      "date": "2025-07-17 17:53:55",
      "link": "https://abdo12249.github.io/1/test1/المشاهده.html?id=akuma-kun&episode=6",
      "image": "https://abdo12249.github.io/1/images/akuma-kun.webp",
      "servers": [
        {
          "serverName": "megamax",
          "url": "https://megamax.me/iframe/LQBCVjdl9OYwR"
        },
        {
          "serverName": "megamax",
          "url": "https://megamax.me/iframe/LQBCVjdl9OYwR"
        },
        {
          "serverName": "mega بدون اعلانات - FHD",
          "url": "https://mega.nz/embed/md9xTAJa!gPtxIhipEscOl1dT_dzrK2XjWCOCwahRy5gpjfexMx0"
        },
        {
          "serverName": "uqload - FHD",
          "url": "https://uqload.net/embed-f4nzlj60so0n.html"
        },
        {
          "serverName": "Google drive - FHD",
          "url": "https://drive.google.com/file/d/1NdteFMx5aVAHUDKJxNGxDHM02eL1Aekc/preview"
        },
        {
          "serverName": "Mp4upload - FHD",
          "url": "https://www.mp4upload.com/embed-yxo99drsrc4b.html"
        }
      ]
    },
    {
      "number": 7,
      "title": "الحلقة 7",
      "date": "2025-07-17 17:53:56",
      "link": "https://abdo12249.github.io/1/test1/المشاهده.html?id=akuma-kun&episode=7",
      "image": "https://abdo12249.github.io/1/images/akuma-kun.webp",
      "servers": [
        {
          "serverName": "megamax",
          "url": "https://megamax.me/iframe/BCEDBX3dyLqVA"
        },
        {
          "serverName": "megamax",
          "url": "https://megamax.me/iframe/BCEDBX3dyLqVA"
        },
        {
          "serverName": "mega بدون اعلانات - FHD",
          "url": "https://mega.nz/embed/6FVABLLL!DNi29wo9Kpyy6nITKD6QYem7ZZtqJD88CqFphxCk4JA"
        },
        {
          "serverName": "uqload - FHD",
          "url": "https://uqload.net/embed-nx0pooxhefow.html"
        },
        {
          "serverName": "Google drive - FHD",
          "url": "https://drive.google.com/file/d/1NEofz0TS_OwWLsWfoWz8Uuii_W6BB-8S/preview"
        },
        {
          "serverName": "Mp4upload - FHD",
          "url": "https://www.mp4upload.com/embed-azfrpev6s416.html"
        }
      ]
    },
    {
      "number": 8,
      "title": "الحلقة 8",
      "date": "2025-07-17 17:53:56",
      "link": "https://abdo12249.github.io/1/test1/المشاهده.html?id=akuma-kun&episode=8",
      "image": "https://abdo12249.github.io/1/images/akuma-kun.webp",
      "servers": [
        {
          "serverName": "megamax",
          "url": "https://megamax.me/iframe/PkUwLuksDD7qQ"
        },
        {
          "serverName": "megamax",
          "url": "https://megamax.me/iframe/PkUwLuksDD7qQ"
        },
        {
          "serverName": "mega بدون اعلانات - FHD",
          "url": "https://mega.nz/embed/KIUVRA5S!xaYNN67YM3AFhEa3jFlhHL7QReCfXw1AiID7EZIQEZ8"
        },
        {
          "serverName": "uqload - FHD",
          "url": "https://uqload.net/embed-1oqboi45p8bq.html"
        },
        {
          "serverName": "Google drive - FHD",
          "url": "https://drive.google.com/file/d/17jeK7PSiZEIVDPk9U1LU4dXigYqNIY9m/preview"
        },
        {
          "serverName": "Mp4upload - FHD",
          "url": "https://www.mp4upload.com/embed-nx87mrffbrjm.html"
        }
      ]
    },
    {
      "number": 9,
      "title": "الحلقة 9",
      "date": "2025-07-17 17:53:55",
      "link": "https://abdo12249.github.io/1/test1/المشاهده.html?id=akuma-kun&episode=9",
      "image": "https://abdo12249.github.io/1/images/akuma-kun.webp",
      "servers": [
        {
          "serverName": "mega بدون اعلانات - FHD",
          "url": "https://mega.nz/embed/3NFgSKpT!1ccqM9o--LnW-QshMyV9vBUcDsFvwE2moYQKjCXcG7k"
        },
        {
          "serverName": "uqload - FHD",
          "url": "https://uqload.net/embed-d1htbei7m321.html"
        },
        {
          "serverName": "Google drive - FHD",
          "url": "https://drive.google.com/file/d/1rnjs4W7lJhBEwdE4oZe9nS0UpCLU9C0T/preview"
        },
        {
          "serverName": "Mp4upload - FHD",
          "url": "https://www.mp4upload.com/embed-jq1hy9nl5jab.html"
        }
      ]
    },
    {
      "number": 10,
      "title": "الحلقة 10",
      "date": "2025-07-17 17:53:55",
      "link": "https://abdo12249.github.io/1/test1/المشاهده.html?id=akuma-kun&episode=10",
      "image": "https://abdo12249.github.io/1/images/akuma-kun.webp",
      "servers": [
        {
          "serverName": "megamax",
          "url": "https://megamax.me/iframe/UrP5GF6FknRir"
        },
        {
          "serverName": "megamax",
          "url": "https://megamax.me/iframe/UrP5GF6FknRir"
        },
        {
          "serverName": "mega بدون اعلانات - FHD",
          "url": "https://mega.nz/embed/bIMXWbpL!5arhN3xqss_PVE6GeaQnw_YyfUoyWo9VG3g-QY0Y24Y"
        },
        {
          "serverName": "uqload - FHD",
          "url": "https://uqload.net/embed-3hj47h33mzm8.html"
        },
        {
          "serverName": "Google drive - FHD",
          "url": "https://drive.google.com/file/d/1bnyxOGOGlTZES4lMJsq9Uk9TrY_zwW0g/preview"
        },
        {
          "serverName": "Mp4upload - FHD",
          "url": "https://www.mp4upload.com/embed-f0rz37v98i6v.html"
        }
      ]
    },
    {
      "number": 11,
      "title": "الحلقة 11",
      "date": "2025-07-17 17:53:56",
      "link": "https://abdo12249.github.io/1/test1/المشاهده.html?id=akuma-kun&episode=11",
      "image": "https://abdo12249.github.io/1/images/akuma-kun.webp",
      "servers": [
        {
          "serverName": "megamax",
          "url": "https://megamax.me/iframe/uMJYeOH5ffBw5"
        },
        {
          "serverName": "megamax",
          "url": "https://megamax.me/iframe/uMJYeOH5ffBw5"
        },
        {
          "serverName": "mega بدون اعلانات - FHD",
          "url": "https://mega.nz/embed/fB1BBTQJ!-cgoHi_CT3eLmp6ogQV_wUvfBRgTrWMEvAoB-87WFYw"
        },
        {
          "serverName": "uqload - FHD",
          "url": "https://uqload.net/embed-rgxccni3js52.html"
        },
        {
          "serverName": "Google drive - FHD",
          "url": "https://drive.google.com/file/d/1uaJzPH3S6e68xzcmwzLYnHyGHBGPWCDM/preview"
        },
        {
          "serverName": "Mp4upload - FHD",
          "url": "https://www.mp4upload.com/embed-0pvrr2h3an6h.html"
        }
      ]
    },
    {
      "number": 12,
      "title": "الحلقة 12",
      "date": "2025-07-17 17:53:55",
      "link": "https://abdo12249.github.io/1/test1/المشاهده.html?id=akuma-kun&episode=12",
      "image": "https://abdo12249.github.io/1/images/akuma-kun.webp",
      "servers": [
        {
          "serverName": "megamax",
          "url": "https://megamax.me/iframe/0f5f8Kmrww2bd"
        },
        {
          "serverName": "megamax",
          "url": "https://megamax.me/iframe/0f5f8Kmrww2bd"
        },
        {
          "serverName": "mega بدون اعلانات - FHD",
          "url": "https://mega.nz/embed/3IdRRQSZ!9wAPIUT1vaypNBtOkDW2y7Ui5lI3I72oywXQKP7WD24"
        },
        {
          "serverName": "uqload - FHD",
          "url": "https://uqload.net/embed-dsk6hm3s1gfl.html"
        },
        {
          "serverName": "Google drive - FHD",
          "url": "https://drive.google.com/file/d/1abSEGopaabCBIBVF2ztsFNl9jSBUl7cG/preview"
        },
        {
          "serverName": "Mp4upload - FHD",
          "url": "https://www.mp4upload.com/embed-4rjt4iafk9ss.html"
        }
      ]
    }
  ]
}