{
  "animeTitle": "Kunoichi Tsubaki no Mune no Uchi الحلقة 1",
  "episodes": [
    {
      "number": 1,
      "title": "الحلقة 1",
      "date": "2025-07-17 20:05:52",
      "link": "https://abdo12249.github.io/1/test1/المشاهده.html?id=kunoichi-tsubaki-no-mune-no-uchi&episode=1",
      "image": "https://abdo12249.github.io/1/images/kunoichi-tsubaki-no-mune-no-uchi.webp",
      "servers": [
        {
          "serverName": "mega بدون اعلانات",
          "url": "https://mega.nz/embed/F3Q1yLyQ!Fvd-HBaSxP1pd38uW1oTL3y39sTajtg_6eo0ezrmIN4"
        },
        {
          "serverName": "ok.ru",
          "url": "https://www.ok.ru/videoembed/3275919133402"
        },
        {
          "serverName": "DoodStream",
          "url": "https://do7go.com/e/0qpo7y2f3599"
        },
        {
          "serverName": "uqload",
          "url": "https://uqload.net/embed-r1bboiqra7qn.html"
        },
        {
          "serverName": "solidfiles",
          "url": "https://www.solidfiles.com/e/5dz6XgA4wvrBa"
        },
        {
          "serverName": "vidbam",
          "url": "https://vadbam.com/embed-piiddo2ah1zw.html"
        },
        {
          "serverName": "Mp4upload",
          "url": "https://www.mp4upload.com/embed-63ik8luw5qiz.html"
        },
        {
          "serverName": "4shared",
          "url": "https://www.4shared.com/web/embed/file/eHn-L1_Giq/"
        },
        {
          "serverName": "uptostream",
          "url": "https://uptostream.com/iframe/qg6oo4q68nbm"
        },
        {
          "serverName": "mega بدون اعلانات - FHD",
          "url": "https://mega.nz/embed/BqpgnBAZ!7nvJNvNtxMKXbJjjPc_ZrnXxjbYDdxaWUhOVcbjGMbY"
        },
        {
          "serverName": "ok.ru - FHD",
          "url": "https://www.ok.ru/videoembed/3275965074138"
        },
        {
          "serverName": "DoodStream - FHD",
          "url": "https://do7go.com/e/dyyk8ute93yj"
        },
        {
          "serverName": "Mp4upload - FHD",
          "url": "https://www.mp4upload.com/embed-8qdh1e59sgt1.html"
        },
        {
          "serverName": "uptostream - FHD",
          "url": "https://uptostream.com/iframe/6tb42o65myzr"
        },
        {
          "serverName": "mega بدون اعلانات - SD",
          "url": "https://mega.nz/embed/IzJEnJAY!rf0LV5FiKkSAOyUUmxbcGYsdT0Rr4eAXCyeaxPaLJ94"
        },
        {
          "serverName": "ok.ru - SD",
          "url": "https://www.ok.ru/videoembed/3275965532890"
        },
        {
          "serverName": "DoodStream - SD",
          "url": "https://do7go.com/e/e58obmkmyfw2"
        },
        {
          "serverName": "Mp4upload - SD",
          "url": "https://www.mp4upload.com/embed-bq78ea89894z.html"
        },
        {
          "serverName": "uptostream - SD",
          "url": "https://uptostream.com/iframe/lcgmcjm3gyuh"
        }
      ]
    },
    {
      "number": 2,
      "title": "الحلقة 2",
      "date": "2025-07-17 20:05:53",
      "link": "https://abdo12249.github.io/1/test1/المشاهده.html?id=kunoichi-tsubaki-no-mune-no-uchi&episode=2",
      "image": "https://abdo12249.github.io/1/images/kunoichi-tsubaki-no-mune-no-uchi.webp",
      "servers": [
        {
          "serverName": "mega بدون اعلانات",
          "url": "https://mega.nz/embed/FgMWXbpT!BR5LmxPLDaY_d0-IEjeVWRhb2uek99bG6lXhtP2dFt8"
        },
        {
          "serverName": "ok.ru",
          "url": "https://www.ok.ru/videoembed/3290780666586"
        },
        {
          "serverName": "DoodStream",
          "url": "https://do7go.com/e/y1597xzhmz8t"
        },
        {
          "serverName": "uqload",
          "url": "https://uqload.net/embed-b9n5ogya6dkk.html"
        },
        {
          "serverName": "vidbam",
          "url": "https://vadbam.com/embed-spxof3ahpigi.html"
        },
        {
          "serverName": "solidfiles",
          "url": "https://www.solidfiles.com/e/dNvyM8AzY5w72"
        },
        {
          "serverName": "Mp4upload",
          "url": "https://www.mp4upload.com/embed-8jxniopa9hsk.html"
        },
        {
          "serverName": "4shared",
          "url": "https://www.4shared.com/web/embed/file/wS4F9uQwea/"
        },
        {
          "serverName": "uptostream",
          "url": "https://uptostream.com/iframe/bvefzo8sshnq"
        },
        {
          "serverName": "mega بدون اعلانات - FHD",
          "url": "https://mega.nz/embed/w9kXwSjK!uhgJ-hi1Ifo6mLFJgxBUEBiR8K3zwd4sWy44mWpPD5s"
        },
        {
          "serverName": "ok.ru - FHD",
          "url": "https://www.ok.ru/videoembed/3290799409882"
        },
        {
          "serverName": "DoodStream - FHD",
          "url": "https://do7go.com/e/9dhnkxo5eog7"
        },
        {
          "serverName": "Mp4upload - FHD",
          "url": "https://www.mp4upload.com/embed-xq2792avibjx.html"
        },
        {
          "serverName": "uptostream - FHD",
          "url": "https://uptostream.com/iframe/2nfylft4mgbd"
        },
        {
          "serverName": "mega بدون اعلانات - SD",
          "url": "https://mega.nz/embed/lttjlC7Z!nLdJWxl5YYnrj25i27fsuN18CmCjTC7B2tEczDerYMw"
        },
        {
          "serverName": "ok.ru - SD",
          "url": "https://www.ok.ru/videoembed/3290804783834"
        },
        {
          "serverName": "DoodStream - SD",
          "url": "https://do7go.com/e/xos9x3r74f55"
        },
        {
          "serverName": "Mp4upload - SD",
          "url": "https://www.mp4upload.com/embed-eq75uggq2967.html"
        },
        {
          "serverName": "uptostream - SD",
          "url": "https://uptostream.com/iframe/h9fv3zuh8jes"
        }
      ]
    },
    {
      "number": 3,
      "title": "الحلقة 3",
      "date": "2025-07-17 20:05:53",
      "link": "https://abdo12249.github.io/1/test1/المشاهده.html?id=kunoichi-tsubaki-no-mune-no-uchi&episode=3",
      "image": "https://abdo12249.github.io/1/images/kunoichi-tsubaki-no-mune-no-uchi.webp",
      "servers": [
        {
          "serverName": "mega بدون اعلانات",
          "url": "https://mega.nz/embed/Jv41RaxZ!mjYzsJsqvtHgRPpeuhddDxq8r3f1jWVydu8eTZri7jI"
        },
        {
          "serverName": "ok.ru",
          "url": "https://www.ok.ru/videoembed/3306703620826"
        },
        {
          "serverName": "DoodStream",
          "url": "https://do7go.com/e/c2w0lvwqz9oq"
        },
        {
          "serverName": "uqload",
          "url": "https://uqload.net/embed-oi41qxvpyizt.html"
        },
        {
          "serverName": "vidbam",
          "url": "https://vadbam.com/embed-ovazu6cnxtf3.html"
        },
        {
          "serverName": "solidfiles",
          "url": "https://www.solidfiles.com/e/2dNYnvVMRXWnv"
        },
        {
          "serverName": "Mp4upload",
          "url": "https://www.mp4upload.com/embed-jyf1qrk1zrka.html"
        },
        {
          "serverName": "4shared",
          "url": "https://www.4shared.com/web/embed/file/JlV9HEuViq/"
        },
        {
          "serverName": "uptostream",
          "url": "https://uptostream.com/iframe/heyjvxnqokzu"
        },
        {
          "serverName": "mega بدون اعلانات - FHD",
          "url": "https://mega.nz/embed/ZvQGCTTY!z6s5EwCx_UVzLdPtg8dRcxwuJmri1EnLTG_CLOI0VCM"
        },
        {
          "serverName": "ok.ru - FHD",
          "url": "https://www.ok.ru/videoembed/3306712926938"
        },
        {
          "serverName": "DoodStream - FHD",
          "url": "https://do7go.com/e/09b1hsth20fy"
        },
        {
          "serverName": "Mp4upload - FHD",
          "url": "https://www.mp4upload.com/embed-v0238pgviwbt.html"
        },
        {
          "serverName": "uptostream - FHD",
          "url": "https://uptostream.com/iframe/qv4rc9h58vkv"
        },
        {
          "serverName": "mega بدون اعلانات - SD",
          "url": "https://mega.nz/embed/1j531bpI!QGrT9_7_zrBsdtgv2C2lqBYtcnh00AlbGvnFAC2h42I"
        },
        {
          "serverName": "ok.ru - SD",
          "url": "https://www.ok.ru/videoembed/3306715679450"
        },
        {
          "serverName": "DoodStream - SD",
          "url": "https://do7go.com/e/6orf7nff2rnx"
        },
        {
          "serverName": "Mp4upload - SD",
          "url": "https://www.mp4upload.com/embed-h7vznt4p9cau.html"
        },
        {
          "serverName": "uptostream - SD",
          "url": "https://uptostream.com/iframe/ane2tkn2r8i5"
        }
      ]
    },
    {
      "number": 4,
      "title": "الحلقة 4",
      "date": "2025-07-17 20:05:53",
      "link": "https://abdo12249.github.io/1/test1/المشاهده.html?id=kunoichi-tsubaki-no-mune-no-uchi&episode=4",
      "image": "https://abdo12249.github.io/1/images/kunoichi-tsubaki-no-mune-no-uchi.webp",
      "servers": [
        {
          "serverName": "mega بدون اعلانات",
          "url": "https://mega.nz/embed/l6RnAIoa!FhEpqkrSLGvhKFINsKLUnggv2tbe9JoLTuUw3MGp_hg"
        },
        {
          "serverName": "ok.ru",
          "url": "https://www.ok.ru/videoembed/3323540998874"
        },
        {
          "serverName": "DoodStream",
          "url": "https://do7go.com/e/uefc6due5cb5"
        },
        {
          "serverName": "uqload",
          "url": "https://uqload.net/embed-ulhuyjs5ozfc.html"
        },
        {
          "serverName": "solidfiles",
          "url": "https://www.solidfiles.com/e/GWM22RLn6nePw"
        },
        {
          "serverName": "vidbam",
          "url": "https://vadbam.com/embed-o2oqqrco270c.html"
        },
        {
          "serverName": "Mp4upload",
          "url": "https://www.mp4upload.com/embed-z2zzhialw9qw.html"
        },
        {
          "serverName": "4shared",
          "url": "https://www.4shared.com/web/embed/file/rb-RQ2sXiq/"
        },
        {
          "serverName": "uptostream",
          "url": "https://uptostream.com/iframe/05euak1c7nle"
        },
        {
          "serverName": "mega بدون اعلانات - FHD",
          "url": "https://mega.nz/embed/47pxhTDT!pSpzK9oYKd_R70k-aZhxxwOhuWuT-ktOFO6Rhou2dZY"
        },
        {
          "serverName": "ok.ru - FHD",
          "url": "https://www.ok.ru/videoembed/3323561773786"
        },
        {
          "serverName": "DoodStream - FHD",
          "url": "https://do7go.com/e/b4x8iq6atnf4"
        },
        {
          "serverName": "Mp4upload - FHD",
          "url": "https://www.mp4upload.com/embed-azrbiv348woz.html"
        },
        {
          "serverName": "uptostream - FHD",
          "url": "https://uptostream.com/iframe/ceqr32dgel52"
        },
        {
          "serverName": "mega بدون اعلانات - SD",
          "url": "https://mega.nz/embed/wuJjgYCC!ztBSmdLdwPwWJGpKJZb-y18b2fzvorLgsZEBI7fGUFA"
        },
        {
          "serverName": "ok.ru - SD",
          "url": "https://www.ok.ru/videoembed/3323577699034"
        },
        {
          "serverName": "DoodStream - SD",
          "url": "https://do7go.com/e/4dw3dp393g38"
        },
        {
          "serverName": "Mp4upload - SD",
          "url": "https://www.mp4upload.com/embed-metjl6tq7vlr.html"
        },
        {
          "serverName": "uptostream - SD",
          "url": "https://uptostream.com/iframe/75eq8u6iejw6"
        }
      ]
    },
    {
      "number": 5,
      "title": "الحلقة 5",
      "date": "2025-07-17 20:05:53",
      "link": "https://abdo12249.github.io/1/test1/المشاهده.html?id=kunoichi-tsubaki-no-mune-no-uchi&episode=5",
      "image": "https://abdo12249.github.io/1/images/kunoichi-tsubaki-no-mune-no-uchi.webp",
      "servers": [
        {
          "serverName": "mega بدون اعلانات",
          "url": "https://mega.nz/embed/1qYSBApB!IuA7ipH3rOBDkojDXAHc8rC4g0JFxAQKx8Zk_8LnlY4"
        },
        {
          "serverName": "ok.ru",
          "url": "https://www.ok.ru/videoembed/3339247880922"
        },
        {
          "serverName": "DoodStream",
          "url": "https://do7go.com/e/8fv5eg5hcp5n"
        },
        {
          "serverName": "uqload",
          "url": "https://uqload.net/embed-s8yzq5izeaqt.html"
        },
        {
          "serverName": "solidfiles",
          "url": "https://www.solidfiles.com/e/vNRVDkZDPegW3"
        },
        {
          "serverName": "vidbam",
          "url": "https://vadbam.com/embed-ar789v0knvhg.html"
        },
        {
          "serverName": "Mp4upload",
          "url": "https://www.mp4upload.com/embed-l5t274j3i9ej.html"
        },
        {
          "serverName": "4shared",
          "url": "https://www.4shared.com/web/embed/file/qPwj4AR0iq/"
        },
        {
          "serverName": "mega بدون اعلانات - FHD",
          "url": "https://mega.nz/embed/m89AAIzZ!gwL20UtWRiCHxwdrlGlFW5LHxxHEqz7MC4fzvCPrIso"
        },
        {
          "serverName": "ok.ru - FHD",
          "url": "https://www.ok.ru/videoembed/3339275864794"
        },
        {
          "serverName": "DoodStream - FHD",
          "url": "https://do7go.com/e/l253g9vhl9fw"
        },
        {
          "serverName": "Mp4upload - FHD",
          "url": "https://www.mp4upload.com/embed-az8n4borofge.html"
        },
        {
          "serverName": "uptostream - FHD",
          "url": "https://uptostream.com/iframe/5jiddc46s1v0"
        },
        {
          "serverName": "mega بدون اعلانات - SD",
          "url": "https://mega.nz/embed/yg9GQZQR!IeBUoOl89ffvFYCQvUaCerKLqi04QtfNyAKzAC0ZSLU"
        },
        {
          "serverName": "ok.ru - SD",
          "url": "https://www.ok.ru/videoembed/3339280845530"
        },
        {
          "serverName": "DoodStream - SD",
          "url": "https://do7go.com/e/xbrygrf5soou"
        },
        {
          "serverName": "Mp4upload - SD",
          "url": "https://www.mp4upload.com/embed-u42s28e4jjfr.html"
        },
        {
          "serverName": "uptostream - SD",
          "url": "https://uptostream.com/iframe/zs0gefpo65ig"
        }
      ]
    },
    {
      "number": 6,
      "title": "الحلقة 6",
      "date": "2025-07-17 20:05:53",
      "link": "https://abdo12249.github.io/1/test1/المشاهده.html?id=kunoichi-tsubaki-no-mune-no-uchi&episode=6",
      "image": "https://abdo12249.github.io/1/images/kunoichi-tsubaki-no-mune-no-uchi.webp",
      "servers": [
        {
          "serverName": "mega بدون اعلانات",
          "url": "https://mega.nz/embed/lsV2QCSR!dZMX6hEDRExZV0L5fES_IXZln6IdU7hUqak2pH8KE9E"
        },
        {
          "serverName": "ok.ru",
          "url": "https://www.ok.ru/videoembed/3355729201882"
        },
        {
          "serverName": "uqload",
          "url": "https://uqload.net/embed-9gwueraabkoz.html"
        },
        {
          "serverName": "DoodStream",
          "url": "https://do7go.com/e/ic9xm1pdti6w"
        },
        {
          "serverName": "vidbam",
          "url": "https://vadbam.com/embed-lcqck5e8bd8c.html"
        },
        {
          "serverName": "Mp4upload",
          "url": "https://www.mp4upload.com/embed-1a6lkqx0deed.html"
        },
        {
          "serverName": "4shared",
          "url": "https://www.4shared.com/web/embed/file/8DqNRggXea/"
        },
        {
          "serverName": "uptostream",
          "url": "https://uptostream.com/iframe/zgobt3b1einb"
        },
        {
          "serverName": "mega بدون اعلانات - FHD",
          "url": "https://mega.nz/embed/g10FDQJS!pq-5yFAolAnVrHHOCjJNcn-t2vwOUa6WQ1LezQav_1U"
        },
        {
          "serverName": "ok.ru - FHD",
          "url": "https://www.ok.ru/videoembed/3355741981402"
        },
        {
          "serverName": "DoodStream - FHD",
          "url": "https://do7go.com/e/d4k00jnl4ln9"
        },
        {
          "serverName": "Mp4upload - FHD",
          "url": "https://www.mp4upload.com/embed-tp3rx6lh4w71.html"
        },
        {
          "serverName": "uptostream - FHD",
          "url": "https://uptostream.com/iframe/jfejtfrbpy4c"
        },
        {
          "serverName": "mega بدون اعلانات - SD",
          "url": "https://mega.nz/embed/9lsj0bgR!_WhO2Hhvsr0muTCUnJb7i8RQsanonFsAWHCEjZDXcAE"
        },
        {
          "serverName": "ok.ru - SD",
          "url": "https://www.ok.ru/videoembed/3355747355354"
        },
        {
          "serverName": "DoodStream - SD",
          "url": "https://do7go.com/e/4aq79anty5qb"
        },
        {
          "serverName": "Mp4upload - SD",
          "url": "https://www.mp4upload.com/embed-h4ymjcvmrs8v.html"
        },
        {
          "serverName": "uptostream - SD",
          "url": "https://uptostream.com/iframe/yvm65gelbwtv"
        }
      ]
    },
    {
      "number": 7,
      "title": "الحلقة 7",
      "date": "2025-07-17 20:05:53",
      "link": "https://abdo12249.github.io/1/test1/المشاهده.html?id=kunoichi-tsubaki-no-mune-no-uchi&episode=7",
      "image": "https://abdo12249.github.io/1/images/kunoichi-tsubaki-no-mune-no-uchi.webp",
      "servers": [
        {
          "serverName": "mega بدون اعلانات",
          "url": "https://mega.nz/embed/8O1yhKTZ!IJqfrxoR4pVHkJjBnLa644ChX6YHL2EzQUWiT_OngnI"
        },
        {
          "serverName": "ok.ru",
          "url": "https://www.ok.ru/videoembed/3371406199514"
        },
        {
          "serverName": "DoodStream",
          "url": "https://do7go.com/e/ybugjio23hvu"
        },
        {
          "serverName": "uqload",
          "url": "https://uqload.net/embed-xzkbhv2pjcwj.html"
        },
        {
          "serverName": "vidbam",
          "url": "https://vadbam.com/embed-m12cv3uqujaf.html"
        },
        {
          "serverName": "solidfiles",
          "url": "https://www.solidfiles.com/e/W8zL5a3aV3jX5"
        },
        {
          "serverName": "Mp4upload",
          "url": "https://www.mp4upload.com/embed-5nm2ly4n1o4i.html"
        },
        {
          "serverName": "4shared",
          "url": "https://www.4shared.com/web/embed/file/JlYYUQRXiq/"
        },
        {
          "serverName": "uptostream",
          "url": "https://uptostream.com/iframe/uyoahu1oq8eg"
        },
        {
          "serverName": "mega بدون اعلانات - FHD",
          "url": "https://mega.nz/embed/UPkAlCKD!V_noqCVUWW08eNR4zYgN1a1Z2ePSsfkuXKuKZRZoJEI"
        },
        {
          "serverName": "ok.ru - FHD",
          "url": "https://www.ok.ru/videoembed/3371425467098"
        },
        {
          "serverName": "DoodStream - FHD",
          "url": "https://do7go.com/e/iyefup2x1akh"
        },
        {
          "serverName": "Mp4upload - FHD",
          "url": "https://www.mp4upload.com/embed-l1s2fqobd36x.html"
        },
        {
          "serverName": "uptostream - FHD",
          "url": "https://uptostream.com/iframe/1h71ejpdfq76"
        },
        {
          "serverName": "mega بدون اعلانات - SD",
          "url": "https://mega.nz/embed/dKk2QLLB!2dRvkHJvRNNcB5C2RFTLtYoNdit-sawBk6tiT8zQJes"
        },
        {
          "serverName": "ok.ru - SD",
          "url": "https://www.ok.ru/videoembed/3371430906586"
        },
        {
          "serverName": "DoodStream - SD",
          "url": "https://do7go.com/e/1tzwpo63tudc"
        },
        {
          "serverName": "Mp4upload - SD",
          "url": "https://www.mp4upload.com/embed-tmpe3uwgadvt.html"
        },
        {
          "serverName": "uptostream - SD",
          "url": "https://uptostream.com/iframe/9fvmh2ffbk63"
        }
      ]
    },
    {
      "number": 8,
      "title": "الحلقة 8",
      "date": "2025-07-17 20:05:53",
      "link": "https://abdo12249.github.io/1/test1/المشاهده.html?id=kunoichi-tsubaki-no-mune-no-uchi&episode=8",
      "image": "https://abdo12249.github.io/1/images/kunoichi-tsubaki-no-mune-no-uchi.webp",
      "servers": [
        {
          "serverName": "mega بدون اعلانات",
          "url": "https://mega.nz/embed/NeUUkISJ!2PkUYVFQAwLKP4bLgg4RSQI1iTQP-46MMkz9p9-8Wag"
        },
        {
          "serverName": "ok.ru",
          "url": "https://www.ok.ru/videoembed/3388581612250"
        },
        {
          "serverName": "uqload",
          "url": "https://uqload.net/embed-5zh032cqeu3o.html"
        },
        {
          "serverName": "DoodStream",
          "url": "https://do7go.com/e/4serc1jp846a"
        },
        {
          "serverName": "vidbam",
          "url": "https://vadbam.com/embed-lyenkykdpe4k.html"
        },
        {
          "serverName": "solidfiles",
          "url": "https://www.solidfiles.com/e/Vxd6VLWmYXRre"
        },
        {
          "serverName": "Mp4upload",
          "url": "https://www.mp4upload.com/embed-06k0gb9lk8zw.html"
        },
        {
          "serverName": "4shared",
          "url": "https://www.4shared.com/web/embed/file/5X0g_xqfiq/"
        },
        {
          "serverName": "uptostream",
          "url": "https://uptostream.com/iframe/f9mivq9xspgs"
        },
        {
          "serverName": "mega بدون اعلانات - FHD",
          "url": "https://mega.nz/embed/0KVC2YgL!QJGCV_uv0KwLafiZMEBT7eRFlGoHb8g68oU8g1gTz6s"
        },
        {
          "serverName": "ok.ru - FHD",
          "url": "https://www.ok.ru/videoembed/3388577876698"
        },
        {
          "serverName": "DoodStream - FHD",
          "url": "https://do7go.com/e/vtc86xnt1kmg"
        },
        {
          "serverName": "Mp4upload - FHD",
          "url": "https://www.mp4upload.com/embed-p3oak2i898z0.html"
        },
        {
          "serverName": "uptostream - FHD",
          "url": "https://uptostream.com/iframe/kdn5in21j6xj"
        },
        {
          "serverName": "mega بدون اعلانات - SD",
          "url": "https://mega.nz/embed/VC0gwQSZ!hYHNQEGzTl8we1HKcwGYjNGyB9k57eXfIct60JrPvLQ"
        },
        {
          "serverName": "ok.ru - SD",
          "url": "https://www.ok.ru/videoembed/3388581939930"
        },
        {
          "serverName": "DoodStream - SD",
          "url": "https://do7go.com/e/f3wivqxw9dm9"
        },
        {
          "serverName": "Mp4upload - SD",
          "url": "https://www.mp4upload.com/embed-ymgpb1vt2yvi.html"
        },
        {
          "serverName": "uptostream - SD",
          "url": "https://uptostream.com/iframe/v9hbh3a87onh"
        }
      ]
    },
    {
      "number": 9,
      "title": "الحلقة 9",
      "date": "2025-07-17 20:05:53",
      "link": "https://abdo12249.github.io/1/test1/المشاهده.html?id=kunoichi-tsubaki-no-mune-no-uchi&episode=9",
      "image": "https://abdo12249.github.io/1/images/kunoichi-tsubaki-no-mune-no-uchi.webp",
      "servers": [
        {
          "serverName": "mega بدون اعلانات",
          "url": "https://mega.nz/embed/4OVC2CSS!-rWQdkSXE_01bvdNh513xTK9Z3cmK6ZxEMNCIx7QQuU"
        },
        {
          "serverName": "ok.ru",
          "url": "https://www.ok.ru/videoembed/3413990443738"
        },
        {
          "serverName": "DoodStream",
          "url": "https://do7go.com/e/93sinml6ulj9"
        },
        {
          "serverName": "uqload",
          "url": "https://uqload.net/embed-i6p4esuqxsyd.html"
        },
        {
          "serverName": "solidfiles",
          "url": "https://www.solidfiles.com/e/NgYmzykPXWxMy"
        },
        {
          "serverName": "vidbam",
          "url": "https://vadbam.com/embed-dpqmyigw83u3.html"
        },
        {
          "serverName": "4shared",
          "url": "https://www.4shared.com/web/embed/file/4vaYzePlea/"
        },
        {
          "serverName": "Mp4upload",
          "url": "https://www.mp4upload.com/embed-wwdaphzbhn44.html"
        },
        {
          "serverName": "uptostream",
          "url": "https://uptostream.com/iframe/2j888f2iae0n"
        },
        {
          "serverName": "mega بدون اعلانات - FHD",
          "url": "https://mega.nz/embed/JPlkDBzB!pDRZXEU3nP_lF-1DiUvz9Ifumry9vN8wEvqbWCe9DQY"
        },
        {
          "serverName": "ok.ru - FHD",
          "url": "https://www.ok.ru/videoembed/3413989460698"
        },
        {
          "serverName": "DoodStream - FHD",
          "url": "https://do7go.com/e/ng6lmi1l2fq2"
        },
        {
          "serverName": "Mp4upload - FHD",
          "url": "https://www.mp4upload.com/embed-bwa7do3lhrt4.html"
        },
        {
          "serverName": "uptostream - FHD",
          "url": "https://uptostream.com/iframe/fxoxoyjc8san"
        },
        {
          "serverName": "mega بدون اعلانات - SD",
          "url": "https://mega.nz/embed/hWEx3R4I!u2vmox40cKF6qpm19suoYXM5MeUae9lX_0tzHGNB2co"
        },
        {
          "serverName": "ok.ru - SD",
          "url": "https://www.ok.ru/videoembed/3413990902490"
        },
        {
          "serverName": "DoodStream - SD",
          "url": "https://do7go.com/e/zo9ntnnvbrg2"
        },
        {
          "serverName": "Mp4upload - SD",
          "url": "https://www.mp4upload.com/embed-4ijrtvffqqy4.html"
        },
        {
          "serverName": "uptostream - SD",
          "url": "https://uptostream.com/iframe/paid6rmrcg9z"
        }
      ]
    },
    {
      "number": 10,
      "title": "الحلقة 10",
      "date": "2025-07-17 20:05:53",
      "link": "https://abdo12249.github.io/1/test1/المشاهده.html?id=kunoichi-tsubaki-no-mune-no-uchi&episode=10",
      "image": "https://abdo12249.github.io/1/images/kunoichi-tsubaki-no-mune-no-uchi.webp",
      "servers": [
        {
          "serverName": "mega بدون اعلانات",
          "url": "https://mega.nz/embed/yTBghJJJ!3dTtvEM1ggo_01N8LB3qfARulrp16kQOw48KG2Gfz6A"
        },
        {
          "serverName": "ok.ru",
          "url": "https://www.ok.ru/videoembed/3435690789594"
        },
        {
          "serverName": "DoodStream",
          "url": "https://do7go.com/e/5acerel56a7k"
        },
        {
          "serverName": "uqload",
          "url": "https://uqload.net/embed-rz2qi785h4q9.html"
        },
        {
          "serverName": "vidbam",
          "url": "https://vadbam.com/embed-e9b06voonny9.html"
        },
        {
          "serverName": "solidfiles",
          "url": "https://www.solidfiles.com/e/3YGgrWxy5vgqv"
        },
        {
          "serverName": "4shared",
          "url": "https://www.4shared.com/web/embed/file/7nPCNs9Uea/"
        },
        {
          "serverName": "Mp4upload",
          "url": "https://www.mp4upload.com/embed-81g7foq7nj3b.html"
        },
        {
          "serverName": "uptostream",
          "url": "https://uptostream.com/iframe/qg963j647zlr"
        },
        {
          "serverName": "mega بدون اعلانات - FHD",
          "url": "https://mega.nz/embed/vPpDQZiB!MqSHyCxPw2CyqLvJaOHB06SeM6WORYVqXON0yY2Sp_A"
        },
        {
          "serverName": "ok.ru - FHD",
          "url": "https://www.ok.ru/videoembed/3435718314714"
        },
        {
          "serverName": "DoodStream - FHD",
          "url": "https://do7go.com/e/o4eyfwkr03m2"
        },
        {
          "serverName": "Mp4upload - FHD",
          "url": "https://www.mp4upload.com/embed-vc8qbbc33umm.html"
        },
        {
          "serverName": "uptostream - FHD",
          "url": "https://uptostream.com/iframe/0duj7hp5lfy8"
        },
        {
          "serverName": "mega بدون اعلانات - SD",
          "url": "https://mega.nz/embed/qa4BBBIZ!bAYJF1YMT7iJ0YE0Jsj7OFGvAGk98jxDnmu2FNC-eH8"
        },
        {
          "serverName": "ok.ru - SD",
          "url": "https://www.ok.ru/videoembed/3435722377946"
        },
        {
          "serverName": "DoodStream - SD",
          "url": "https://do7go.com/e/vgvjzwwigazi"
        },
        {
          "serverName": "Mp4upload - SD",
          "url": "https://www.mp4upload.com/embed-ltabjcc12qko.html"
        },
        {
          "serverName": "uptostream - SD",
          "url": "https://uptostream.com/iframe/spletgyl97qf"
        }
      ]
    },
    {
      "number": 11,
      "title": "الحلقة 11",
      "date": "2025-07-17 20:05:53",
      "link": "https://abdo12249.github.io/1/test1/المشاهده.html?id=kunoichi-tsubaki-no-mune-no-uchi&episode=11",
      "image": "https://abdo12249.github.io/1/images/kunoichi-tsubaki-no-mune-no-uchi.webp",
      "servers": [
        {
          "serverName": "mega بدون اعلانات",
          "url": "https://mega.nz/embed/pP0m0RKa!IcyigyDkTuT_NLCTvTcOBAD4sHoqR-jHmOVhUTDpNvk"
        },
        {
          "serverName": "ok.ru",
          "url": "https://www.ok.ru/videoembed/3459897952986"
        },
        {
          "serverName": "uqload",
          "url": "https://uqload.net/embed-35bngs9d3ea8.html"
        },
        {
          "serverName": "DoodStream",
          "url": "https://do7go.com/e/4rt8z4bm6u6b"
        },
        {
          "serverName": "solidfiles",
          "url": "https://www.solidfiles.com/e/3Y3dWeMerePDy"
        },
        {
          "serverName": "vidbam",
          "url": "https://vadbam.com/embed-irw3kv4yblp6.html"
        },
        {
          "serverName": "Mp4upload",
          "url": "https://www.mp4upload.com/embed-eirjzeoum3m5.html"
        },
        {
          "serverName": "4shared",
          "url": "https://www.4shared.com/web/embed/file/omqvSc2Vea/"
        },
        {
          "serverName": "uptostream",
          "url": "https://uptostream.com/iframe/8htr4hs9o337"
        },
        {
          "serverName": "mega بدون اعلانات - FHD",
          "url": "https://mega.nz/embed/5OtWzYBD!UlAE4ZCZxpr1by3DgAqQWNBD96Z3U-KimcLGrR6ANeo"
        },
        {
          "serverName": "ok.ru - FHD",
          "url": "https://www.ok.ru/videoembed/3459915778778"
        },
        {
          "serverName": "DoodStream - FHD",
          "url": "https://do7go.com/e/5vvo688d0uej"
        },
        {
          "serverName": "Mp4upload - FHD",
          "url": "https://www.mp4upload.com/embed-grmeedv4qgef.html"
        },
        {
          "serverName": "uptostream - FHD",
          "url": "https://uptostream.com/iframe/qibd1h9ruaig"
        },
        {
          "serverName": "mega بدون اعلانات - SD",
          "url": "https://mega.nz/embed/1P0BlL4R!bipnR_JTlQr38DxmWT33e2rtEJ7DuKl1RowNy1MJ3ts"
        },
        {
          "serverName": "ok.ru - SD",
          "url": "https://www.ok.ru/videoembed/3459921021658"
        },
        {
          "serverName": "DoodStream - SD",
          "url": "https://do7go.com/e/sb94cfk1wo5p"
        },
        {
          "serverName": "Mp4upload - SD",
          "url": "https://www.mp4upload.com/embed-7zz6zpvm520i.html"
        },
        {
          "serverName": "uptostream - SD",
          "url": "https://uptostream.com/iframe/utjc4rldda2a"
        }
      ]
    },
    {
      "number": 12,
      "title": "الحلقة 12",
      "date": "2025-07-17 20:05:53",
      "link": "https://abdo12249.github.io/1/test1/المشاهده.html?id=kunoichi-tsubaki-no-mune-no-uchi&episode=12",
      "image": "https://abdo12249.github.io/1/images/kunoichi-tsubaki-no-mune-no-uchi.webp",
      "servers": [
        {
          "serverName": "mega بدون اعلانات",
          "url": "https://mega.nz/embed/cGUSxYpA!DOeJ69xwzbyk18F17ESuLNcAOP9hE2YDQUs6kH-DQ58"
        },
        {
          "serverName": "ok.ru",
          "url": "https://www.ok.ru/videoembed/3484498528986"
        },
        {
          "serverName": "DoodStream",
          "url": "https://do7go.com/e/li457an582mr"
        },
        {
          "serverName": "uqload",
          "url": "https://uqload.net/embed-l1l083krti24.html"
        },
        {
          "serverName": "vidbam",
          "url": "https://vadbam.com/embed-6785q95ypqze.html"
        },
        {
          "serverName": "solidfiles",
          "url": "https://www.solidfiles.com/e/eZnKjBpXdYMnV"
        },
        {
          "serverName": "4shared",
          "url": "https://www.4shared.com/web/embed/file/JQ7gVedqea/"
        },
        {
          "serverName": "Mp4upload",
          "url": "https://www.mp4upload.com/embed-cqqya0o4etdd.html"
        },
        {
          "serverName": "uptostream",
          "url": "https://uptostream.com/iframe/j27ll86qsfm2"
        },
        {
          "serverName": "mega بدون اعلانات - FHD",
          "url": "https://mega.nz/embed/0P9jwAab!WU4OfwEGsRhbYw8ef6kvxNGZsePckQvoVaaTAYwLSEc"
        },
        {
          "serverName": "ok.ru - FHD",
          "url": "https://www.ok.ru/videoembed/3484511636186"
        },
        {
          "serverName": "DoodStream - FHD",
          "url": "https://do7go.com/e/0nf5buugybwe"
        },
        {
          "serverName": "Mp4upload - FHD",
          "url": "https://www.mp4upload.com/embed-n6q8uq0dgp40.html"
        },
        {
          "serverName": "uptostream - FHD",
          "url": "https://uptostream.com/iframe/vrq0xx16qpcb"
        },
        {
          "serverName": "mega بدون اعلانات - SD",
          "url": "https://mega.nz/embed/AXlT1TiS!sa4GcGLzAYADg4sBRaJVe2GJIAsP9fUWcUTr-ulNtJs"
        },
        {
          "serverName": "ok.ru - SD",
          "url": "https://www.ok.ru/videoembed/3484515699418"
        },
        {
          "serverName": "DoodStream - SD",
          "url": "https://do7go.com/e/807loyz8ftml"
        },
        {
          "serverName": "Mp4upload - SD",
          "url": "https://www.mp4upload.com/embed-1nq2c8wy421b.html"
        },
        {
          "serverName": "uptostream - SD",
          "url": "https://uptostream.com/iframe/jp471m0u0a98"
        }
      ]
    },
    {
      "number": 13,
      "title": "الحلقة 13",
      "date": "2025-07-17 20:05:53",
      "link": "https://abdo12249.github.io/1/test1/المشاهده.html?id=kunoichi-tsubaki-no-mune-no-uchi&episode=13",
      "image": "https://abdo12249.github.io/1/images/kunoichi-tsubaki-no-mune-no-uchi.webp",
      "servers": [
        {
          "serverName": "mega بدون اعلانات",
          "url": "https://mega.nz/embed/AKEARQBJ!5dTL6x5eA0rYWbW4bAdRtFZBM0LYyhfn-yJVZ3NSlns"
        },
        {
          "serverName": "ok.ru",
          "url": "https://www.ok.ru/videoembed/3503040498394"
        },
        {
          "serverName": "DoodStream",
          "url": "https://do7go.com/e/utmp7hispoiz"
        },
        {
          "serverName": "uqload",
          "url": "https://uqload.net/embed-e1cuqda36za4.html"
        },
        {
          "serverName": "vidbam",
          "url": "https://vadbam.com/embed-h4i4pz362jfk.html"
        },
        {
          "serverName": "solidfiles",
          "url": "https://www.solidfiles.com/e/WQdxmvGg5rj2g"
        },
        {
          "serverName": "4shared",
          "url": "https://www.4shared.com/web/embed/file/-5-RQOGoea/"
        },
        {
          "serverName": "Mp4upload",
          "url": "https://www.mp4upload.com/embed-cyy7hjdk3n1a.html"
        },
        {
          "serverName": "uptostream",
          "url": "https://uptostream.com/iframe/aaa8asd23h1x"
        },
        {
          "serverName": "mega بدون اعلانات - FHD",
          "url": "https://mega.nz/embed/1fEVmTxB!rgEevEOHuEkqBeH79K6hdh9tV8bCegW-vzxdSLIo17s"
        },
        {
          "serverName": "ok.ru - FHD",
          "url": "https://www.ok.ru/videoembed/3503040301786"
        },
        {
          "serverName": "DoodStream - FHD",
          "url": "https://do7go.com/e/2xq8mt8c38s3"
        },
        {
          "serverName": "Mp4upload - FHD",
          "url": "https://www.mp4upload.com/embed-0ewq17mgc01f.html"
        },
        {
          "serverName": "uptostream - FHD",
          "url": "https://uptostream.com/iframe/akeya9fdopvm"
        },
        {
          "serverName": "mega بدون اعلانات - SD",
          "url": "https://mega.nz/embed/ca02AAwD!bNIEgnHcTHQthe1N6MvjOhYEhjUetXX_2C7EfR7HFnM"
        },
        {
          "serverName": "ok.ru - SD",
          "url": "https://www.ok.ru/videoembed/3503040695002"
        },
        {
          "serverName": "DoodStream - SD",
          "url": "https://do7go.com/e/4hksww0zqob6"
        },
        {
          "serverName": "Mp4upload - SD",
          "url": "https://www.mp4upload.com/embed-zrfihx7yxlae.html"
        },
        {
          "serverName": "uptostream - SD",
          "url": "https://uptostream.com/iframe/5eilcufnmptt"
        }
      ]
    }
  ]
}